mcpe_query/__init__.py
mcpe_query/query.py
py_mcpe_query-0.2.1.dist-info/LICENSE
py_mcpe_query-0.2.1.dist-info/METADATA
py_mcpe_query-0.2.1.dist-info/WHEEL
py_mcpe_query-0.2.1.dist-info/top_level.txt
py_mcpe_query-0.2.1.dist-info/RECORD
