Metadata-Version: 2.1
Name: py-mcpe-query
Version: 0.2.1
Summary: Query a Minecraft: bedrock edition server easily
Home-page: https://github.com/w-gao/py-mcpe-query
Author: w-gao
Author-email: dev@wlgao.com
License: MIT
Keywords: mcpe minecraft mcpeserver
Platform: UNKNOWN
Classifier: Development Status :: 3 - Alpha
Classifier: Environment :: Console
Classifier: Intended Audience :: Developers
Classifier: Intended Audience :: System Administrators
Classifier: License :: OSI Approved :: MIT License
Classifier: Natural Language :: English
Classifier: Programming Language :: Python :: 3.6
Classifier: Topic :: Software Development :: Libraries :: Python Modules
Classifier: Topic :: System :: Networking
Requires-Python: >=3.6
